Mikrotik_Connector/__init__.py
Mikrotik_Connector/connector.py
Mikrotik_Connector-0.2.dist-info/METADATA
Mikrotik_Connector-0.2.dist-info/WHEEL
Mikrotik_Connector-0.2.dist-info/top_level.txt
Mikrotik_Connector-0.2.dist-info/RECORD
