Metadata-Version: 2.1
Name: Mikrotik_Connector
Version: 0.2
Summary: A python-based SSH API for MikroTik devices
Home-page: https://github.com/MacPal2002/Mikrotik_Connector
Author: MacPal2002
Author-email: maciek.palenica@outlook.com
Classifier: Development Status :: 3 - Alpha
Classifier: Intended Audience :: Developers
Classifier: License :: OSI Approved :: MIT License
Classifier: Programming Language :: Python :: 3
Classifier: Programming Language :: Python :: 3.6
Classifier: Programming Language :: Python :: 3.7
Classifier: Programming Language :: Python :: 3.8
Classifier: Programming Language :: Python :: 3.9
Requires-Dist: paramiko
Requires-Dist: packaging
